Metadata-Version: 2.1
Name: odoo13-addon-queue-job
Version: 13.0.3.11.2
Summary: Job Queue
Home-page: https://github.com/OCA/queue
Author: Camptocamp,ACSONE SA/NV,Odoo Community Association (OCA)
Author-email: support@odoo-community.org
License: LGPL-3
Platform: UNKNOWN
Classifier: Programming Language :: Python
Classifier: Framework :: Odoo
Classifier: Framework :: Odoo :: 13.0
Classifier: License :: OSI Approved :: GNU Lesser General Public License v3 (LGPLv3)
Classifier: Development Status :: 6 - Mature
Requires-Python: >=3.5
Requires-Dist: odoo <13.1dev,>=13.0a
Requires-Dist: requests
